.coveragerc
COPYING
COPYING.LESSER
MANIFEST.in
Makefile
README.md
SConstruct
VERSION
requirements.txt
setup.py
tox.ini
zetup.cfg
moretools/__init__.py
moretools/_cached.py
moretools/_caller.py
moretools/_collections.py
moretools/_common.py
moretools/_context.py
moretools/_del.py
moretools/_dict.py
moretools/_empty.py
moretools/_filter.py
moretools/_get.py
moretools/_has.py
moretools/_is.py
moretools/_lazy.py
moretools/_log.py
moretools/_map.py
moretools/_mapper.py
moretools/_multi.py
moretools/_multidict.py
moretools/_multisimpledict.py
moretools/_operand.py
moretools/_operator.py
moretools/_pop.py
moretools/_query.py
moretools/_repeat.py
moretools/_set.py
moretools/_simpledict.py
moretools/_simpletree.py
moretools/_star.py
moretools/_string.py
moretools/_take.py
moretools/_tester.py
moretools/_types.py
moretools/_undefined.py
moretools/_xmlrpc.py
moretools/boolean.py
moretools/func.py
moretools/mapping.py
moretools/test_func.py
moretools/zetup_config.py
moretools.egg-info/PKG-INFO
moretools.egg-info/SOURCES.txt
moretools.egg-info/dependency_links.txt
moretools.egg-info/requires.txt
moretools.egg-info/top_level.txt
test/test_dict.py
test/test_simpledict.py
test/test_string.py
test/bool/conftest.py
test/bool/test_bool.py