Metadata-Version: 1.1
Name: moretools
Version: 0.1.9
Summary: MORE Overly Reusable Essentials for python
Home-page: https://github.com/zimmermanncode/moretools
Author: Stefan Zimmermann
Author-email: user@zimmermann.co
License: LGPLv3
Keywords: tools,itertools,functools,operator,collections,iterator,iteration,functional,filter,map,repeat,query,tuple,list,set,dict,simpledict,frozen,struct,dictset,dictzip,simpledictset,simpledictzip,camelize,decamelize,isidentifier,identifier,python3
Platform: UNKNOWN
Classifier: Development Status :: 3 - Alpha
Classifier: Intended Audience :: Developers
Classifier: License :: OSI Approved :: GNU Library or Lesser General Public License (LGPL)
Classifier: Operating System :: OS Independent
Classifier: Topic :: Software Development
Classifier: Topic :: Utilities
Classifier: Programming Language :: Python
Classifier: Programming Language :: Python :: 2.7
Classifier: Programming Language :: Python :: 3.4
Classifier: Programming Language :: Python :: 3.5
Classifier: Programming Language :: Python :: 3.6
